nxdomain/__init__.py
nxdomain/__main__.py
nxdomain-1.0.2.dist-info/LICENSE
nxdomain-1.0.2.dist-info/METADATA
nxdomain-1.0.2.dist-info/WHEEL
nxdomain-1.0.2.dist-info/entry_points.txt
nxdomain-1.0.2.dist-info/top_level.txt
nxdomain-1.0.2.dist-info/zip-safe
nxdomain-1.0.2.dist-info/RECORD
