Metadata-Version: 2.1
Name: nxdomain
Version: 1.0.2
Summary: Downloads and converts domain block lists for use with BIND/named RPZ files or dnsmasq host files.
Home-page: https://github.com/zopieux/nxdomain
Author: Alexandre Macabies
Author-email: web@zopieux.com
License: UNKNOWN
Project-URL: Bug Reports, https://github.com/zopieux/nxdomain/issues
Project-URL: Source, https://github.com/zopieux/nxdomain
Platform: UNKNOWN
Classifier: Development Status :: 3 - Alpha
Classifier: Intended Audience :: Developers
Classifier: License :: OSI Approved :: GNU General Public License v3 or later (GPLv3+)
Classifier: Programming Language :: Python :: 3
Classifier: Programming Language :: Python :: 3.8
Classifier: Programming Language :: Python :: 3.9
Requires-Dist: dnspython (~=2.0)
